[{"id": 3288204, "name": "Alien Robot with Blasters", "url": "https://api.thingiverse.com/things/3288204", "public_url": "https://www.thingiverse.com/thing:3288204", "created_at": "2018-12-16T03:32:21+00:00", "thumbnail": "https://cdn.thingiverse.com/renders/e8/c9/7f/02/fe/275344a288639e39af12100c4db580fc_display_large.JPG", "preview_image": "https://cdn.thingiverse.com/renders/e8/c9/7f/02/fe/275344a288639e39af12100c4db580fc_preview_card.JPG", "creator": {"id": 325497, "name": "mz4250", "first_name": "Miguel", "last_name": "Zavala", "url": "https://api.thingiverse.com/users/mz4250", "public_url": "https://www.thingiverse.com/mz4250", "thumbnail": "https://cdn.thingiverse.com/renders/7f/80/a3/0a/5e/Manly1_thumb_medium.jpg", "count_of_followers": 18222, "count_of_following": 78, "count_of_designs": 584, "accepts_tips": true, "is_following": false, "location": "", "cover": "https://cdn.thingiverse.com/renders/8a/1e/7f/05/ab/dice2_preview_large.jpg"}, "is_private": null, "is_purchased": null, "is_published": null, "comment_count": null, "like_count": 57, "tags": [{"name": "alien", "tag": "alien", "url": "https://api.thingiverse.com/tags/alien", "count": 1651, "things_url": "https://api.thingiverse.com/tags/alien/things", "absolute_url": "https://www.thingiverse.com/tag:alien"}, {"name": "robot", "tag": "robot", "url": "https://api.thingiverse.com/tags/robot", "count": 6505, "things_url": "https://api.thingiverse.com/tags/robot/things", "absolute_url": "https://www.thingiverse.com/tag:robot"}, {"name": "robots", "tag": "robots", "url": "https://api.thingiverse.com/tags/robots", "count": 531, "things_url": "https://api.thingiverse.com/tags/robots/things", "absolute_url": "https://www.thingiverse.com/tag:robots"}], "is_nsfw": false}, {"id": 3288182, "name": "Orc Boar Rider", "url": "https://api.thingiverse.com/things/3288182", "public_url": "https://www.thingiverse.com/thing:3288182", "created_at": "2018-12-16T03:15:39+00:00", "thumbnail": "https://cdn.thingiverse.com/renders/97/b5/46/78/bf/df8c89ef154e4fae201bdd25f8c9818f_display_large.JPG", "preview_image": "https://cdn.thingiverse.com/renders/97/b5/46/78/bf/df8c89ef154e4fae201bdd25f8c9818f_preview_card.JPG", "creator": {"id": 325497, "name": "mz4250", "first_name": "Miguel", "last_name": "Zavala", "url": "https://api.thingiverse.com/users/mz4250", "public_url": "https://www.thingiverse.com/mz4250", "thumbnail": "https://cdn.thingiverse.com/renders/7f/80/a3/0a/5e/Manly1_thumb_medium.jpg", "count_of_followers": 18222, "count_of_following": 78, "count_of_designs": 584, "accepts_tips": true, "is_following": false, "location": "", "cover": "https://cdn.thingiverse.com/renders/8a/1e/7f/05/ab/dice2_preview_large.jpg"}, "is_private": null, "is_purchased": null, "is_published": null, "comment_count": null, "like_count": 190, "tags": [{"name": "boar", "tag": "boar", "url": "https://api.thingiverse.com/tags/boar", "count": 54, "things_url": "https://api.thingiverse.com/tags/boar/things", "absolute_url": "https://www.thingiverse.com/tag:boar"}, {"name": "orc", "tag": "orc", "url": "https://api.thingiverse.com/tags/orc", "count": 427, "things_url": "https://api.thingiverse.com/tags/orc/things", "absolute_url": "https://www.thingiverse.com/tag:orc"}], "is_nsfw": false}, {"id": 3288175, "name": "Wicker Man", "url": "https://api.thingiverse.com/things/3288175", "public_url": "https://www.thingiverse.com/thing:3288175", "created_at": "2018-12-16T03:12:10+00:00", "thumbnail": "https://cdn.thingiverse.com/renders/53/1e/7f/bc/33/cb7c4fb073e1a356e979c44a6a61cdff_display_large.jpg", "preview_image": "https://cdn.thingiverse.com/renders/53/1e/7f/bc/33/cb7c4fb073e1a356e979c44a6a61cdff_preview_card.jpg", "creator": {"id": 325497, "name": "mz4250", "first_name": "Miguel", "last_name": "Zavala", "url": "https://api.thingiverse.com/users/mz4250", "public_url": "https://www.thingiverse.com/mz4250", "thumbnail": "https://cdn.thingiverse.com/renders/7f/80/a3/0a/5e/Manly1_thumb_medium.jpg", "count_of_followers": 18222, "count_of_following": 78, "count_of_designs": 584, "accepts_tips": true, "is_following": false, "location": "", "cover": "https://cdn.thingiverse.com/renders/8a/1e/7f/05/ab/dice2_preview_large.jpg"}, "is_private": null, "is_purchased": null, "is_published": null, "comment_count": null, "like_count": 86, "tags": [{"name": "construct", "tag": "construct", "url": "https://api.thingiverse.com/tags/construct", "count": 76, "things_url": "https://api.thingiverse.com/tags/construct/things", "absolute_url": "https://www.thingiverse.com/tag:construct"}, {"name": "dnd", "tag": "dnd", "url": "https://api.thingiverse.com/tags/dnd", "count": 11070, "things_url": "https://api.thingiverse.com/tags/dnd/things", "absolute_url": "https://www.thingiverse.com/tag:dnd"}, {"name": "giant", "tag": "giant", "url": "https://api.thingiverse.com/tags/giant", "count": 300, "things_url": "https://api.thingiverse.com/tags/giant/things", "absolute_url": "https://www.thingiverse.com/tag:giant"}, {"name": "wicker man", "tag": "wicker_man", "url": "https://api.thingiverse.com/tags/wicker_man", "count": 1, "things_url": "https://api.thingiverse.com/tags/wicker_man/things", "absolute_url": "https://www.thingiverse.com/tag:wicker_man"}], "is_nsfw": false}, {"id": 3287498, "name": "Horned Dragon and the Orc Warchief Rider", "url": "https://api.thingiverse.com/things/3287498", "public_url": "https://www.thingiverse.com/thing:3287498", "created_at": "2018-12-15T20:45:44+00:00", "thumbnail": "https://cdn.thingiverse.com/renders/10/a3/1e/fb/45/cd16f08516234a7e82c31f06b0583ced_display_large.JPG", "preview_image": "https://cdn.thingiverse.com/renders/10/a3/1e/fb/45/cd16f08516234a7e82c31f06b0583ced_preview_card.JPG", "creator": {"id": 325497, "name": "mz4250", "first_name": "Miguel", "last_name": "Zavala", "url": "https://api.thingiverse.com/users/mz4250", "public_url": "https://www.thingiverse.com/mz4250", "thumbnail": "https://cdn.thingiverse.com/renders/7f/80/a3/0a/5e/Manly1_thumb_medium.jpg", "count_of_followers": 18222, "count_of_following": 78, "count_of_designs": 584, "accepts_tips": true, "is_following": false, "location": "", "cover": "https://cdn.thingiverse.com/renders/8a/1e/7f/05/ab/dice2_preview_large.jpg"}, "is_private": null, "is_purchased": null, "is_published": null, "comment_count": null, "like_count": 445, "tags": [{"name": "dnd", "tag": "dnd", "url": "https://api.thingiverse.com/tags/dnd", "count": 11070, "things_url": "https://api.thingiverse.com/tags/dnd/things", "absolute_url": "https://www.thingiverse.com/tag:dnd"}, {"name": "dragons", "tag": "dragons", "url": "https://api.thingiverse.com/tags/dragons", "count": 637, "things_url": "https://api.thingiverse.com/tags/dragons/things", "absolute_url": "https://www.thingiverse.com/tag:dragons"}, {"name": "dungeons and dragons", "tag": "dungeons_and_dragons", "url": "https://api.thingiverse.com/tags/dungeons_and_dragons", "count": 8466, "things_url": "https://api.thingiverse.com/tags/dungeons_and_dragons/things", "absolute_url": "https://www.thingiverse.com/tag:dungeons_and_dragons"}, {"name": "orc", "tag": "orc", "url": "https://api.thingiverse.com/tags/orc", "count": 427, "things_url": "https://api.thingiverse.com/tags/orc/things", "absolute_url": "https://www.thingiverse.com/tag:orc"}], "is_nsfw": false}, {"id": 3211969, "name": "Night Dragon", "url": "https://api.thingiverse.com/things/3211969", "public_url": "https://www.thingiverse.com/thing:3211969", "created_at": "2018-11-12T20:54:53+00:00", "thumbnail": "https://cdn.thingiverse.com/renders/99/d5/d7/bb/2b/a9449f1c656f03ea7e2064c2c24ad037_display_large.jpg", "preview_image": "https://cdn.thingiverse.com/renders/99/d5/d7/bb/2b/a9449f1c656f03ea7e2064c2c24ad037_preview_card.jpg", "creator": {"id": 325497, "name": "mz4250", "first_name": "Miguel", "last_name": "Zavala", "url": "https://api.thingiverse.com/users/mz4250", "public_url": "https://www.thingiverse.com/mz4250", "thumbnail": "https://cdn.thingiverse.com/renders/7f/80/a3/0a/5e/Manly1_thumb_medium.jpg", "count_of_followers": 18222, "count_of_following": 78, "count_of_designs": 584, "accepts_tips": true, "is_following": false, "location": "", "cover": "https://cdn.thingiverse.com/renders/8a/1e/7f/05/ab/dice2_preview_large.jpg"}, "is_private": null, "is_purchased": null, "is_published": null, "comment_count": 23, "like_count": 682, "tags": [{"name": "dnd", "tag": "dnd", "url": "https://api.thingiverse.com/tags/dnd", "count": 11070, "things_url": "https://api.thingiverse.com/tags/dnd/things", "absolute_url": "https://www.thingiverse.com/tag:dnd"}, {"name": "dragon", "tag": "dragon", "url": "https://api.thingiverse.com/tags/dragon", "count": 2317, "things_url": "https://api.thingiverse.com/tags/dragon/things", "absolute_url": "https://www.thingiverse.com/tag:dragon"}, {"name": "dungeons and dragons", "tag": "dungeons_and_dragons", "url": "https://api.thingiverse.com/tags/dungeons_and_dragons", "count": 8466, "things_url": "https://api.thingiverse.com/tags/dungeons_and_dragons/things", "absolute_url": "https://www.thingiverse.com/tag:dungeons_and_dragons"}, {"name": "pathfinder", "tag": "pathfinder", "url": "https://api.thingiverse.com/tags/pathfinder", "count": 4005, "things_url": "https://api.thingiverse.com/tags/pathfinder/things", "absolute_url": "https://www.thingiverse.com/tag:pathfinder"}], "is_nsfw": false}, {"id": 3190718, "name": "The Heroes from \"Dice, Camera, Action!\"", "url": "https://api.thingiverse.com/things/3190718", "public_url": "https://www.thingiverse.com/thing:3190718", "created_at": "2018-11-02T03:00:30+00:00", "thumbnail": "https://cdn.thingiverse.com/renders/f5/e6/9d/a7/fb/911e98043723db8dcbebdc1b6b7af400_display_large.jpg", "preview_image": "https://cdn.thingiverse.com/renders/f5/e6/9d/a7/fb/911e98043723db8dcbebdc1b6b7af400_preview_card.jpg", "creator": {"id": 325497, "name": "mz4250", "first_name": "Miguel", "last_name": "Zavala", "url": "https://api.thingiverse.com/users/mz4250", "public_url": "https://www.thingiverse.com/mz4250", "thumbnail": "https://cdn.thingiverse.com/renders/7f/80/a3/0a/5e/Manly1_thumb_medium.jpg", "count_of_followers": 18222, "count_of_following": 78, "count_of_designs": 584, "accepts_tips": true, "is_following": false, "location": "", "cover": "https://cdn.thingiverse.com/renders/8a/1e/7f/05/ab/dice2_preview_large.jpg"}, "is_private": null, "is_purchased": null, "is_published": null, "comment_count": 12, "like_count": 321, "tags": [{"name": "dd", "tag": "dd", "url": "https://api.thingiverse.com/tags/dd", "count": 1, "things_url": "https://api.thingiverse.com/tags/dd/things", "absolute_url": "https://www.thingiverse.com/tag:dd"}, {"name": "dnd", "tag": "dnd", "url": "https://api.thingiverse.com/tags/dnd", "count": 11070, "things_url": "https://api.thingiverse.com/tags/dnd/things", "absolute_url": "https://www.thingiverse.com/tag:dnd"}, {"name": "dungeons and dragons", "tag": "dungeons_and_dragons", "url": "https://api.thingiverse.com/tags/dungeons_and_dragons", "count": 8466, "things_url": "https://api.thingiverse.com/tags/dungeons_and_dragons/things", "absolute_url": "https://www.thingiverse.com/tag:dungeons_and_dragons"}, {"name": "paladin", "tag": "paladin", "url": "https://api.thingiverse.com/tags/paladin", "count": 191, "things_url": "https://api.thingiverse.com/tags/paladin/things", "absolute_url": "https://www.thingiverse.com/tag:paladin"}], "is_nsfw": false}, {"id": 3177545, "name": "Party Ogre! ", "url": "https://api.thingiverse.com/things/3177545", "public_url": "https://www.thingiverse.com/thing:3177545", "created_at": "2018-10-26T12:14:33+00:00", "thumbnail": "https://cdn.thingiverse.com/renders/a9/5e/6e/02/e7/4ada6e5a53f0225ea574536c3b10d16b_display_large.JPG", "preview_image": "https://cdn.thingiverse.com/renders/a9/5e/6e/02/e7/4ada6e5a53f0225ea574536c3b10d16b_preview_card.JPG", "creator": {"id": 325497, "name": "mz4250", "first_name": "Miguel", "last_name": "Zavala", "url": "https://api.thingiverse.com/users/mz4250", "public_url": "https://www.thingiverse.com/mz4250", "thumbnail": "https://cdn.thingiverse.com/renders/7f/80/a3/0a/5e/Manly1_thumb_medium.jpg", "count_of_followers": 18222, "count_of_following": 78, "count_of_designs": 584, "accepts_tips": true, "is_following": false, "location": "", "cover": "https://cdn.thingiverse.com/renders/8a/1e/7f/05/ab/dice2_preview_large.jpg"}, "is_private": null, "is_purchased": null, "is_published": null, "comment_count": 5, "like_count": 276, "tags": [{"name": "beer", "tag": "beer", "url": "https://api.thingiverse.com/tags/beer", "count": 1672, "things_url": "https://api.thingiverse.com/tags/beer/things", "absolute_url": "https://www.thingiverse.com/tag:beer"}, {"name": "booze", "tag": "booze", "url": "https://api.thingiverse.com/tags/booze", "count": 24, "things_url": "https://api.thingiverse.com/tags/booze/things", "absolute_url": "https://www.thingiverse.com/tag:booze"}, {"name": "dd", "tag": "dd", "url": "https://api.thingiverse.com/tags/dd", "count": 1, "things_url": "https://api.thingiverse.com/tags/dd/things", "absolute_url": "https://www.thingiverse.com/tag:dd"}, {"name": "dnd", "tag": "dnd", "url": "https://api.thingiverse.com/tags/dnd", "count": 11070, "things_url": "https://api.thingiverse.com/tags/dnd/things", "absolute_url": "https://www.thingiverse.com/tag:dnd"}, {"name": "fun", "tag": "fun", "url": "https://api.thingiverse.com/tags/fun", "count": 3942, "things_url": "https://api.thingiverse.com/tags/fun/things", "absolute_url": "https://www.thingiverse.com/tag:fun"}, {"name": "giant", "tag": "giant", "url": "https://api.thingiverse.com/tags/giant", "count": 300, "things_url": "https://api.thingiverse.com/tags/giant/things", "absolute_url": "https://www.thingiverse.com/tag:giant"}, {"name": "ogre", "tag": "ogre", "url": "https://api.thingiverse.com/tags/ogre", "count": 203, "things_url": "https://api.thingiverse.com/tags/ogre/things", "absolute_url": "https://www.thingiverse.com/tag:ogre"}, {"name": "party", "tag": "party", "url": "https://api.thingiverse.com/tags/party", "count": 466, "things_url": "https://api.thingiverse.com/tags/party/things", "absolute_url": "https://www.thingiverse.com/tag:party"}, {"name": "pathfinder", "tag": "pathfinder", "url": "https://api.thingiverse.com/tags/pathfinder", "count": 4005, "things_url": "https://api.thingiverse.com/tags/pathfinder/things", "absolute_url": "https://www.thingiverse.com/tag:pathfinder"}, {"name": "Troll", "tag": "troll", "url": "https://api.thingiverse.com/tags/troll", "count": 241, "things_url": "https://api.thingiverse.com/tags/troll/things", "absolute_url": "https://www.thingiverse.com/tag:Troll"}, {"name": "whiskey", "tag": "whiskey", "url": "https://api.thingiverse.com/tags/whiskey", "count": 59, "things_url": "https://api.thingiverse.com/tags/whiskey/things", "absolute_url": "https://www.thingiverse.com/tag:whiskey"}], "is_nsfw": false}, {"id": 3112418, "name": "Kitsune Collection", "url": "https://api.thingiverse.com/things/3112418", "public_url": "https://www.thingiverse.com/thing:3112418", "created_at": "2018-09-21T12:39:46+00:00", "thumbnail": "https://cdn.thingiverse.com/renders/4b/a1/cb/8b/21/f2b21055caefbcba770c380ab96eea49_display_large.jpg", "preview_image": "https://cdn.thingiverse.com/renders/4b/a1/cb/8b/21/f2b21055caefbcba770c380ab96eea49_preview_card.jpg", "creator": {"id": 325497, "name": "mz4250", "first_name": "Miguel", "last_name": "Zavala", "url": "https://api.thingiverse.com/users/mz4250", "public_url": "https://www.thingiverse.com/mz4250", "thumbnail": "https://cdn.thingiverse.com/renders/7f/80/a3/0a/5e/Manly1_thumb_medium.jpg", "count_of_followers": 18222, "count_of_following": 78, "count_of_designs": 584, "accepts_tips": true, "is_following": false, "location": "", "cover": "https://cdn.thingiverse.com/renders/8a/1e/7f/05/ab/dice2_preview_large.jpg"}, "is_private": null, "is_purchased": null, "is_published": null, "comment_count": 4, "like_count": 405, "tags": [{"name": "dnd", "tag": "dnd", "url": "https://api.thingiverse.com/tags/dnd", "count": 11070, "things_url": "https://api.thingiverse.com/tags/dnd/things", "absolute_url": "https://www.thingiverse.com/tag:dnd"}, {"name": "dnd mini", "tag": "dnd_mini", "url": "https://api.thingiverse.com/tags/dnd_mini", "count": 897, "things_url": "https://api.thingiverse.com/tags/dnd_mini/things", "absolute_url": "https://www.thingiverse.com/tag:dnd_mini"}, {"name": "fox", "tag": "fox", "url": "https://api.thingiverse.com/tags/fox", "count": 467, "things_url": "https://api.thingiverse.com/tags/fox/things", "absolute_url": "https://www.thingiverse.com/tag:fox"}, {"name": "Kitsune", "tag": "kitsune", "url": "https://api.thingiverse.com/tags/kitsune", "count": 19, "things_url": "https://api.thingiverse.com/tags/kitsune/things", "absolute_url": "https://www.thingiverse.com/tag:Kitsune"}, {"name": "mage", "tag": "mage", "url": "https://api.thingiverse.com/tags/mage", "count": 316, "things_url": "https://api.thingiverse.com/tags/mage/things", "absolute_url": "https://www.thingiverse.com/tag:mage"}, {"name": "ranger", "tag": "ranger", "url": "https://api.thingiverse.com/tags/ranger", "count": 290, "things_url": "https://api.thingiverse.com/tags/ranger/things", "absolute_url": "https://www.thingiverse.com/tag:ranger"}, {"name": "rogue", "tag": "rogue", "url": "https://api.thingiverse.com/tags/rogue", "count": 237, "things_url": "https://api.thingiverse.com/tags/rogue/things", "absolute_url": "https://www.thingiverse.com/tag:rogue"}], "is_nsfw": false}, {"id": 3105131, "name": "Swag Goblin", "url": "https://api.thingiverse.com/things/3105131", "public_url": "https://www.thingiverse.com/thing:3105131", "created_at": "2018-09-17T11:23:54+00:00", "thumbnail": "https://cdn.thingiverse.com/renders/57/94/46/9f/69/6b9aa5850901705bfb1c54ea0960d755_display_large.jpg", "preview_image": "https://cdn.thingiverse.com/renders/57/94/46/9f/69/6b9aa5850901705bfb1c54ea0960d755_preview_card.jpg", "creator": {"id": 325497, "name": "mz4250", "first_name": "Miguel", "last_name": "Zavala", "url": "https://api.thingiverse.com/users/mz4250", "public_url": "https://www.thingiverse.com/mz4250", "thumbnail": "https://cdn.thingiverse.com/renders/7f/80/a3/0a/5e/Manly1_thumb_medium.jpg", "count_of_followers": 18222, "count_of_following": 78, "count_of_designs": 584, "accepts_tips": true, "is_following": false, "location": "", "cover": "https://cdn.thingiverse.com/renders/8a/1e/7f/05/ab/dice2_preview_large.jpg"}, "is_private": null, "is_purchased": null, "is_published": null, "comment_count": 2, "like_count": 206, "tags": [{"name": "dnd", "tag": "dnd", "url": "https://api.thingiverse.com/tags/dnd", "count": 11070, "things_url": "https://api.thingiverse.com/tags/dnd/things", "absolute_url": "https://www.thingiverse.com/tag:dnd"}, {"name": "goblin", "tag": "goblin", "url": "https://api.thingiverse.com/tags/goblin", "count": 465, "things_url": "https://api.thingiverse.com/tags/goblin/things", "absolute_url": "https://www.thingiverse.com/tag:goblin"}], "is_nsfw": false}, {"id": 3088949, "name": "Yeti Collection", "url": "https://api.thingiverse.com/things/3088949", "public_url": "https://www.thingiverse.com/thing:3088949", "created_at": "2018-09-07T22:46:54+00:00", "thumbnail": "https://cdn.thingiverse.com/renders/e0/ec/c9/2f/74/97336514b8107a4d3bcd532c5ce72f9d_display_large.JPG", "preview_image": "https://cdn.thingiverse.com/renders/e0/ec/c9/2f/74/97336514b8107a4d3bcd532c5ce72f9d_preview_card.JPG", "creator": {"id": 325497, "name": "mz4250", "first_name": "Miguel", "last_name": "Zavala", "url": "https://api.thingiverse.com/users/mz4250", "public_url": "https://www.thingiverse.com/mz4250", "thumbnail": "https://cdn.thingiverse.com/renders/7f/80/a3/0a/5e/Manly1_thumb_medium.jpg", "count_of_followers": 18222, "count_of_following": 78, "count_of_designs": 584, "accepts_tips": true, "is_following": false, "location": "", "cover": "https://cdn.thingiverse.com/renders/8a/1e/7f/05/ab/dice2_preview_large.jpg"}, "is_private": null, "is_purchased": null, "is_published": null, "comment_count": null, "like_count": 241, "tags": [{"name": "bigfoot", "tag": "bigfoot", "url": "https://api.thingiverse.com/tags/bigfoot", "count": 39, "things_url": "https://api.thingiverse.com/tags/bigfoot/things", "absolute_url": "https://www.thingiverse.com/tag:bigfoot"}, {"name": "dnd", "tag": "dnd", "url": "https://api.thingiverse.com/tags/dnd", "count": 11070, "things_url": "https://api.thingiverse.com/tags/dnd/things", "absolute_url": "https://www.thingiverse.com/tag:dnd"}, {"name": "yeti", "tag": "yeti", "url": "https://api.thingiverse.com/tags/yeti", "count": 235, "things_url": "https://api.thingiverse.com/tags/yeti/things", "absolute_url": "https://www.thingiverse.com/tag:yeti"}], "is_nsfw": false}, {"id": 3088672, "name": "Orc Warrior", "url": "https://api.thingiverse.com/things/3088672", "public_url": "https://www.thingiverse.com/thing:3088672", "created_at": "2018-09-07T19:41:21+00:00", "thumbnail": "https://cdn.thingiverse.com/renders/d7/eb/1b/f3/7f/1c6aad833621a58cea7989d7f7ea4ec7_display_large.jpg", "preview_image": "https://cdn.thingiverse.com/renders/d7/eb/1b/f3/7f/1c6aad833621a58cea7989d7f7ea4ec7_preview_card.jpg", "creator": {"id": 325497, "name": "mz4250", "first_name": "Miguel", "last_name": "Zavala", "url": "https://api.thingiverse.com/users/mz4250", "public_url": "https://www.thingiverse.com/mz4250", "thumbnail": "https://cdn.thingiverse.com/renders/7f/80/a3/0a/5e/Manly1_thumb_medium.jpg", "count_of_followers": 18222, "count_of_following": 78, "count_of_designs": 584, "accepts_tips": true, "is_following": false, "location": "", "cover": "https://cdn.thingiverse.com/renders/8a/1e/7f/05/ab/dice2_preview_large.jpg"}, "is_private": null, "is_purchased": null, "is_published": null, "comment_count": 9, "like_count": 566, "tags": [{"name": "dnd", "tag": "dnd", "url": "https://api.thingiverse.com/tags/dnd", "count": 11070, "things_url": "https://api.thingiverse.com/tags/dnd/things", "absolute_url": "https://www.thingiverse.com/tag:dnd"}, {"name": "orc", "tag": "orc", "url": "https://api.thingiverse.com/tags/orc", "count": 427, "things_url": "https://api.thingiverse.com/tags/orc/things", "absolute_url": "https://www.thingiverse.com/tag:orc"}], "is_nsfw": false}, {"id": 3065856, "name": "The Gang from \"Its Always Sunny in Philadelphia\" - The Night Man Cometh D&D Miniature Set", "url": "https://api.thingiverse.com/things/3065856", "public_url": "https://www.thingiverse.com/thing:3065856", "created_at": "2018-08-24T21:48:32+00:00", "thumbnail": "https://cdn.thingiverse.com/renders/72/a8/ce/7b/14/7e91aa3d1c829ed84729bd6f9f546c84_display_large.jpg", "preview_image": "https://cdn.thingiverse.com/renders/72/a8/ce/7b/14/7e91aa3d1c829ed84729bd6f9f546c84_preview_card.jpg", "creator": {"id": 325497, "name": "mz4250", "first_name": "Miguel", "last_name": "Zavala", "url": "https://api.thingiverse.com/users/mz4250", "public_url": "https://www.thingiverse.com/mz4250", "thumbnail": "https://cdn.thingiverse.com/renders/7f/80/a3/0a/5e/Manly1_thumb_medium.jpg", "count_of_followers": 18222, "count_of_following": 78, "count_of_designs": 584, "accepts_tips": true, "is_following": false, "location": "", "cover": "https://cdn.thingiverse.com/renders/8a/1e/7f/05/ab/dice2_preview_large.jpg"}, "is_private": null, "is_purchased": null, "is_published": null, "comment_count": 61, "like_count": 567, "tags": [{"name": "A bird", "tag": "a_bird", "url": "https://api.thingiverse.com/tags/a_bird", "count": 1, "things_url": "https://api.thingiverse.com/tags/a_bird/things", "absolute_url": "https://www.thingiverse.com/tag:A_bird"}, {"name": "dd", "tag": "dd", "url": "https://api.thingiverse.com/tags/dd", "count": 1, "things_url": "https://api.thingiverse.com/tags/dd/things", "absolute_url": "https://www.thingiverse.com/tag:dd"}, {"name": "Dayman", "tag": "dayman", "url": "https://api.thingiverse.com/tags/dayman", "count": 1, "things_url": "https://api.thingiverse.com/tags/dayman/things", "absolute_url": "https://www.thingiverse.com/tag:Dayman"}, {"name": "dnd", "tag": "dnd", "url": "https://api.thingiverse.com/tags/dnd", "count": 11070, "things_url": "https://api.thingiverse.com/tags/dnd/things", "absolute_url": "https://www.thingiverse.com/tag:dnd"}, {"name": "everyone", "tag": "everyone", "url": "https://api.thingiverse.com/tags/everyone", "count": 11, "things_url": "https://api.thingiverse.com/tags/everyone/things", "absolute_url": "https://www.thingiverse.com/tag:everyone"}, {"name": "Friendship", "tag": "friendship", "url": "https://api.thingiverse.com/tags/friendship", "count": 37, "things_url": "https://api.thingiverse.com/tags/friendship/things", "absolute_url": "https://www.thingiverse.com/tag:Friendship"}, {"name": "Its Always Sunny", "tag": "its_always_sunny", "url": "https://api.thingiverse.com/tags/its_always_sunny", "count": 5, "things_url": "https://api.thingiverse.com/tags/its_always_sunny/things", "absolute_url": "https://www.thingiverse.com/tag:Its_Always_Sunny"}, {"name": "karate", "tag": "karate", "url": "https://api.thingiverse.com/tags/karate", "count": 59, "things_url": "https://api.thingiverse.com/tags/karate/things", "absolute_url": "https://www.thingiverse.com/tag:karate"}, {"name": "Nightman", "tag": "nightman", "url": "https://api.thingiverse.com/tags/nightman", "count": 1, "things_url": "https://api.thingiverse.com/tags/nightman/things", "absolute_url": "https://www.thingiverse.com/tag:Nightman"}, {"name": "ninja", "tag": "ninja", "url": "https://api.thingiverse.com/tags/ninja", "count": 501, "things_url": "https://api.thingiverse.com/tags/ninja/things", "absolute_url": "https://www.thingiverse.com/tag:ninja"}, {"name": "philadelphia", "tag": "philadelphia", "url": "https://api.thingiverse.com/tags/philadelphia", "count": 50, "things_url": "https://api.thingiverse.com/tags/philadelphia/things", "absolute_url": "https://www.thingiverse.com/tag:philadelphia"}, {"name": "the gang", "tag": "the_gang", "url": "https://api.thingiverse.com/tags/the_gang", "count": 2, "things_url": "https://api.thingiverse.com/tags/the_gang/things", "absolute_url": "https://www.thingiverse.com/tag:the_gang"}, {"name": "the sun", "tag": "the_sun", "url": "https://api.thingiverse.com/tags/the_sun", "count": 2, "things_url": "https://api.thingiverse.com/tags/the_sun/things", "absolute_url": "https://www.thingiverse.com/tag:the_sun"}, {"name": "toll", "tag": "toll", "url": "https://api.thingiverse.com/tags/toll", "count": 14, "things_url": "https://api.thingiverse.com/tags/toll/things", "absolute_url": "https://www.thingiverse.com/tag:toll"}, {"name": "Troll", "tag": "troll", "url": "https://api.thingiverse.com/tags/troll", "count": 241, "things_url": "https://api.thingiverse.com/tags/troll/things", "absolute_url": "https://www.thingiverse.com/tag:Troll"}], "is_nsfw": false}, {"id": 3058902, "name": "Water Pieces for Tabletop Gaming", "url": "https://api.thingiverse.com/things/3058902", "public_url": "https://www.thingiverse.com/thing:3058902", "created_at": "2018-08-20T12:38:43+00:00", "thumbnail": "https://cdn.thingiverse.com/renders/69/b9/1b/1b/fc/fdaf5e751039846ca01354f3721f0c6a_display_large.jpg", "preview_image": "https://cdn.thingiverse.com/renders/69/b9/1b/1b/fc/fdaf5e751039846ca01354f3721f0c6a_preview_card.jpg", "creator": {"id": 325497, "name": "mz4250", "first_name": "Miguel", "last_name": "Zavala", "url": "https://api.thingiverse.com/users/mz4250", "public_url": "https://www.thingiverse.com/mz4250", "thumbnail": "https://cdn.thingiverse.com/renders/7f/80/a3/0a/5e/Manly1_thumb_medium.jpg", "count_of_followers": 18222, "count_of_following": 78, "count_of_designs": 584, "accepts_tips": true, "is_following": false, "location": "", "cover": "https://cdn.thingiverse.com/renders/8a/1e/7f/05/ab/dice2_preview_large.jpg"}, "is_private": null, "is_purchased": null, "is_published": null, "comment_count": 4, "like_count": 108, "tags": [], "is_nsfw": false}, {"id": 3058864, "name": "Halfling Druid on a Bear", "url": "https://api.thingiverse.com/things/3058864", "public_url": "https://www.thingiverse.com/thing:3058864", "created_at": "2018-08-20T12:15:20+00:00", "thumbnail": "https://cdn.thingiverse.com/renders/ae/04/3c/d8/ce/ce6fd2b612a42a209a74e225a4a23ebc_display_large.JPG", "preview_image": "https://cdn.thingiverse.com/renders/ae/04/3c/d8/ce/ce6fd2b612a42a209a74e225a4a23ebc_preview_card.JPG", "creator": {"id": 325497, "name": "mz4250", "first_name": "Miguel", "last_name": "Zavala", "url": "https://api.thingiverse.com/users/mz4250", "public_url": "https://www.thingiverse.com/mz4250", "thumbnail": "https://cdn.thingiverse.com/renders/7f/80/a3/0a/5e/Manly1_thumb_medium.jpg", "count_of_followers": 18222, "count_of_following": 78, "count_of_designs": 584, "accepts_tips": true, "is_following": false, "location": "", "cover": "https://cdn.thingiverse.com/renders/8a/1e/7f/05/ab/dice2_preview_large.jpg"}, "is_private": null, "is_purchased": null, "is_published": null, "comment_count": 2, "like_count": 173, "tags": [{"name": "bear", "tag": "bear", "url": "https://api.thingiverse.com/tags/bear", "count": 954, "things_url": "https://api.thingiverse.com/tags/bear/things", "absolute_url": "https://www.thingiverse.com/tag:bear"}, {"name": "dnd", "tag": "dnd", "url": "https://api.thingiverse.com/tags/dnd", "count": 11070, "things_url": "https://api.thingiverse.com/tags/dnd/things", "absolute_url": "https://www.thingiverse.com/tag:dnd"}, {"name": "druid", "tag": "druid", "url": "https://api.thingiverse.com/tags/druid", "count": 149, "things_url": "https://api.thingiverse.com/tags/druid/things", "absolute_url": "https://www.thingiverse.com/tag:druid"}, {"name": "halfling", "tag": "halfling", "url": "https://api.thingiverse.com/tags/halfling", "count": 107, "things_url": "https://api.thingiverse.com/tags/halfling/things", "absolute_url": "https://www.thingiverse.com/tag:halfling"}], "is_nsfw": false}, {"id": 3053715, "name": "Grave Titan", "url": "https://api.thingiverse.com/things/3053715", "public_url": "https://www.thingiverse.com/thing:3053715", "created_at": "2018-08-17T08:58:22+00:00", "thumbnail": "https://cdn.thingiverse.com/renders/60/2c/33/5c/6b/6afa4076809c1eba33c5b7cd2292b3d5_display_large.JPG", "preview_image": "https://cdn.thingiverse.com/renders/60/2c/33/5c/6b/6afa4076809c1eba33c5b7cd2292b3d5_preview_card.JPG", "creator": {"id": 325497, "name": "mz4250", "first_name": "Miguel", "last_name": "Zavala", "url": "https://api.thingiverse.com/users/mz4250", "public_url": "https://www.thingiverse.com/mz4250", "thumbnail": "https://cdn.thingiverse.com/renders/7f/80/a3/0a/5e/Manly1_thumb_medium.jpg", "count_of_followers": 18222, "count_of_following": 78, "count_of_designs": 584, "accepts_tips": true, "is_following": false, "location": "", "cover": "https://cdn.thingiverse.com/renders/8a/1e/7f/05/ab/dice2_preview_large.jpg"}, "is_private": null, "is_purchased": null, "is_published": null, "comment_count": 2, "like_count": 158, "tags": [{"name": "dd", "tag": "dd", "url": "https://api.thingiverse.com/tags/dd", "count": 1, "things_url": "https://api.thingiverse.com/tags/dd/things", "absolute_url": "https://www.thingiverse.com/tag:dd"}, {"name": "dnd", "tag": "dnd", "url": "https://api.thingiverse.com/tags/dnd", "count": 11070, "things_url": "https://api.thingiverse.com/tags/dnd/things", "absolute_url": "https://www.thingiverse.com/tag:dnd"}, {"name": "dungeons and dragons", "tag": "dungeons_and_dragons", "url": "https://api.thingiverse.com/tags/dungeons_and_dragons", "count": 8466, "things_url": "https://api.thingiverse.com/tags/dungeons_and_dragons/things", "absolute_url": "https://www.thingiverse.com/tag:dungeons_and_dragons"}, {"name": "giant", "tag": "giant", "url": "https://api.thingiverse.com/tags/giant", "count": 300, "things_url": "https://api.thingiverse.com/tags/giant/things", "absolute_url": "https://www.thingiverse.com/tag:giant"}, {"name": "titan", "tag": "titan", "url": "https://api.thingiverse.com/tags/titan", "count": 1009, "things_url": "https://api.thingiverse.com/tags/titan/things", "absolute_url": "https://www.thingiverse.com/tag:titan"}, {"name": "zombie", "tag": "zombie", "url": "https://api.thingiverse.com/tags/zombie", "count": 575, "things_url": "https://api.thingiverse.com/tags/zombie/things", "absolute_url": "https://www.thingiverse.com/tag:zombie"}], "is_nsfw": false}, {"id": 3044588, "name": "Elric of Melnibon\u00e9 ", "url": "https://api.thingiverse.com/things/3044588", "public_url": "https://www.thingiverse.com/thing:3044588", "created_at": "2018-08-11T15:43:41+00:00", "thumbnail": "https://cdn.thingiverse.com/renders/0d/ab/43/2d/34/0882f48c02e60fc97e605dadf5fcef11_display_large.JPG", "preview_image": "https://cdn.thingiverse.com/renders/0d/ab/43/2d/34/0882f48c02e60fc97e605dadf5fcef11_preview_card.JPG", "creator": {"id": 325497, "name": "mz4250", "first_name": "Miguel", "last_name": "Zavala", "url": "https://api.thingiverse.com/users/mz4250", "public_url": "https://www.thingiverse.com/mz4250", "thumbnail": "https://cdn.thingiverse.com/renders/7f/80/a3/0a/5e/Manly1_thumb_medium.jpg", "count_of_followers": 18222, "count_of_following": 78, "count_of_designs": 584, "accepts_tips": true, "is_following": false, "location": "", "cover": "https://cdn.thingiverse.com/renders/8a/1e/7f/05/ab/dice2_preview_large.jpg"}, "is_private": null, "is_purchased": null, "is_published": null, "comment_count": 2, "like_count": 215, "tags": [{"name": "dd", "tag": "dd", "url": "https://api.thingiverse.com/tags/dd", "count": 1, "things_url": "https://api.thingiverse.com/tags/dd/things", "absolute_url": "https://www.thingiverse.com/tag:dd"}, {"name": "dnd", "tag": "dnd", "url": "https://api.thingiverse.com/tags/dnd", "count": 11070, "things_url": "https://api.thingiverse.com/tags/dnd/things", "absolute_url": "https://www.thingiverse.com/tag:dnd"}, {"name": "dungeons and dragons", "tag": "dungeons_and_dragons", "url": "https://api.thingiverse.com/tags/dungeons_and_dragons", "count": 8466, "things_url": "https://api.thingiverse.com/tags/dungeons_and_dragons/things", "absolute_url": "https://www.thingiverse.com/tag:dungeons_and_dragons"}, {"name": "Elric", "tag": "elric", "url": "https://api.thingiverse.com/tags/elric", "count": 6, "things_url": "https://api.thingiverse.com/tags/elric/things", "absolute_url": "https://www.thingiverse.com/tag:Elric"}], "is_nsfw": false}, {"id": 3044032, "name": "Subek from \"Tome of Beasts\" ", "url": "https://api.thingiverse.com/things/3044032", "public_url": "https://www.thingiverse.com/thing:3044032", "created_at": "2018-08-11T04:24:09+00:00", "thumbnail": "https://cdn.thingiverse.com/renders/af/3c/04/f3/1e/6afa4076809c1eba33c5b7cd2292b3d5_display_large.JPG", "preview_image": "https://cdn.thingiverse.com/renders/af/3c/04/f3/1e/6afa4076809c1eba33c5b7cd2292b3d5_preview_card.JPG", "creator": {"id": 325497, "name": "mz4250", "first_name": "Miguel", "last_name": "Zavala", "url": "https://api.thingiverse.com/users/mz4250", "public_url": "https://www.thingiverse.com/mz4250", "thumbnail": "https://cdn.thingiverse.com/renders/7f/80/a3/0a/5e/Manly1_thumb_medium.jpg", "count_of_followers": 18222, "count_of_following": 78, "count_of_designs": 584, "accepts_tips": true, "is_following": false, "location": "", "cover": "https://cdn.thingiverse.com/renders/8a/1e/7f/05/ab/dice2_preview_large.jpg"}, "is_private": null, "is_purchased": null, "is_published": null, "comment_count": 6, "like_count": 257, "tags": [{"name": "crocodile", "tag": "crocodile", "url": "https://api.thingiverse.com/tags/crocodile", "count": 125, "things_url": "https://api.thingiverse.com/tags/crocodile/things", "absolute_url": "https://www.thingiverse.com/tag:crocodile"}, {"name": "dd", "tag": "dd", "url": "https://api.thingiverse.com/tags/dd", "count": 1, "things_url": "https://api.thingiverse.com/tags/dd/things", "absolute_url": "https://www.thingiverse.com/tag:dd"}, {"name": "dnd", "tag": "dnd", "url": "https://api.thingiverse.com/tags/dnd", "count": 11070, "things_url": "https://api.thingiverse.com/tags/dnd/things", "absolute_url": "https://www.thingiverse.com/tag:dnd"}, {"name": "dungeons and dragons", "tag": "dungeons_and_dragons", "url": "https://api.thingiverse.com/tags/dungeons_and_dragons", "count": 8466, "things_url": "https://api.thingiverse.com/tags/dungeons_and_dragons/things", "absolute_url": "https://www.thingiverse.com/tag:dungeons_and_dragons"}, {"name": "kobold press", "tag": "kobold_press", "url": "https://api.thingiverse.com/tags/kobold_press", "count": 13, "things_url": "https://api.thingiverse.com/tags/kobold_press/things", "absolute_url": "https://www.thingiverse.com/tag:kobold_press"}, {"name": "subek", "tag": "subek", "url": "https://api.thingiverse.com/tags/subek", "count": 1, "things_url": "https://api.thingiverse.com/tags/subek/things", "absolute_url": "https://www.thingiverse.com/tag:subek"}], "is_nsfw": false}, {"id": 3042436, "name": "SPACESHIP!!!!", "url": "https://api.thingiverse.com/things/3042436", "public_url": "https://www.thingiverse.com/thing:3042436", "created_at": "2018-08-10T01:29:56+00:00", "thumbnail": "https://cdn.thingiverse.com/renders/d2/23/48/22/fc/b1424463fccc7a955813ef51bdbf128a_display_large.jpg", "preview_image": "https://cdn.thingiverse.com/renders/d2/23/48/22/fc/b1424463fccc7a955813ef51bdbf128a_preview_card.jpg", "creator": {"id": 325497, "name": "mz4250", "first_name": "Miguel", "last_name": "Zavala", "url": "https://api.thingiverse.com/users/mz4250", "public_url": "https://www.thingiverse.com/mz4250", "thumbnail": "https://cdn.thingiverse.com/renders/7f/80/a3/0a/5e/Manly1_thumb_medium.jpg", "count_of_followers": 18222, "count_of_following": 78, "count_of_designs": 584, "accepts_tips": true, "is_following": false, "location": "", "cover": "https://cdn.thingiverse.com/renders/8a/1e/7f/05/ab/dice2_preview_large.jpg"}, "is_private": null, "is_purchased": null, "is_published": null, "comment_count": 16, "like_count": 88, "tags": [{"name": "Spaceship", "tag": "spaceship", "url": "https://api.thingiverse.com/tags/spaceship", "count": 2630, "things_url": "https://api.thingiverse.com/tags/spaceship/things", "absolute_url": "https://www.thingiverse.com/tag:Spaceship"}], "is_nsfw": false}, {"id": 3030914, "name": "Bahamut - God of all Metallic Dragons! ", "url": "https://api.thingiverse.com/things/3030914", "public_url": "https://www.thingiverse.com/thing:3030914", "created_at": "2018-08-02T06:48:34+00:00", "thumbnail": "https://cdn.thingiverse.com/renders/dc/d1/b5/30/99/c1920a29e3f41524a09c4939f28e3a9e_display_large.jpg", "preview_image": "https://cdn.thingiverse.com/renders/dc/d1/b5/30/99/c1920a29e3f41524a09c4939f28e3a9e_preview_card.jpg", "creator": {"id": 325497, "name": "mz4250", "first_name": "Miguel", "last_name": "Zavala", "url": "https://api.thingiverse.com/users/mz4250", "public_url": "https://www.thingiverse.com/mz4250", "thumbnail": "https://cdn.thingiverse.com/renders/7f/80/a3/0a/5e/Manly1_thumb_medium.jpg", "count_of_followers": 18222, "count_of_following": 78, "count_of_designs": 584, "accepts_tips": true, "is_following": false, "location": "", "cover": "https://cdn.thingiverse.com/renders/8a/1e/7f/05/ab/dice2_preview_large.jpg"}, "is_private": null, "is_purchased": null, "is_published": null, "comment_count": 42, "like_count": 2180, "tags": [{"name": "bahamut", "tag": "bahamut", "url": "https://api.thingiverse.com/tags/bahamut", "count": 3, "things_url": "https://api.thingiverse.com/tags/bahamut/things", "absolute_url": "https://www.thingiverse.com/tag:bahamut"}, {"name": "dnd", "tag": "dnd", "url": "https://api.thingiverse.com/tags/dnd", "count": 11070, "things_url": "https://api.thingiverse.com/tags/dnd/things", "absolute_url": "https://www.thingiverse.com/tag:dnd"}, {"name": "dragon", "tag": "dragon", "url": "https://api.thingiverse.com/tags/dragon", "count": 2317, "things_url": "https://api.thingiverse.com/tags/dragon/things", "absolute_url": "https://www.thingiverse.com/tag:dragon"}, {"name": "dragons", "tag": "dragons", "url": "https://api.thingiverse.com/tags/dragons", "count": 637, "things_url": "https://api.thingiverse.com/tags/dragons/things", "absolute_url": "https://www.thingiverse.com/tag:dragons"}, {"name": "dungeons and dragons", "tag": "dungeons_and_dragons", "url": "https://api.thingiverse.com/tags/dungeons_and_dragons", "count": 8466, "things_url": "https://api.thingiverse.com/tags/dungeons_and_dragons/things", "absolute_url": "https://www.thingiverse.com/tag:dungeons_and_dragons"}, {"name": "dungeonsanddragons", "tag": "dungeonsanddragons", "url": "https://api.thingiverse.com/tags/dungeonsanddragons", "count": 136, "things_url": "https://api.thingiverse.com/tags/dungeonsanddragons/things", "absolute_url": "https://www.thingiverse.com/tag:dungeonsanddragons"}], "is_nsfw": false}, {"id": 3018884, "name": "Kraken 2", "url": "https://api.thingiverse.com/things/3018884", "public_url": "https://www.thingiverse.com/thing:3018884", "created_at": "2018-07-25T01:45:33+00:00", "thumbnail": "https://cdn.thingiverse.com/renders/e8/ed/cc/b4/e5/22e964fdcddf1cbec04c8535e292d6e9_display_large.jpg", "preview_image": "https://cdn.thingiverse.com/renders/e8/ed/cc/b4/e5/22e964fdcddf1cbec04c8535e292d6e9_preview_card.jpg", "creator": {"id": 325497, "name": "mz4250", "first_name": "Miguel", "last_name": "Zavala", "url": "https://api.thingiverse.com/users/mz4250", "public_url": "https://www.thingiverse.com/mz4250", "thumbnail": "https://cdn.thingiverse.com/renders/7f/80/a3/0a/5e/Manly1_thumb_medium.jpg", "count_of_followers": 18222, "count_of_following": 78, "count_of_designs": 584, "accepts_tips": true, "is_following": false, "location": "", "cover": "https://cdn.thingiverse.com/renders/8a/1e/7f/05/ab/dice2_preview_large.jpg"}, "is_private": null, "is_purchased": null, "is_published": null, "comment_count": 12, "like_count": 460, "tags": [{"name": "dd", "tag": "dd", "url": "https://api.thingiverse.com/tags/dd", "count": 1, "things_url": "https://api.thingiverse.com/tags/dd/things", "absolute_url": "https://www.thingiverse.com/tag:dd"}, {"name": "dnd", "tag": "dnd", "url": "https://api.thingiverse.com/tags/dnd", "count": 11070, "things_url": "https://api.thingiverse.com/tags/dnd/things", "absolute_url": "https://www.thingiverse.com/tag:dnd"}, {"name": "DnD Tiles", "tag": "dnd_tiles", "url": "https://api.thingiverse.com/tags/dnd_tiles", "count": 1155, "things_url": "https://api.thingiverse.com/tags/dnd_tiles/things", "absolute_url": "https://www.thingiverse.com/tag:DnD_Tiles"}, {"name": "dungeons and dragons", "tag": "dungeons_and_dragons", "url": "https://api.thingiverse.com/tags/dungeons_and_dragons", "count": 8466, "things_url": "https://api.thingiverse.com/tags/dungeons_and_dragons/things", "absolute_url": "https://www.thingiverse.com/tag:dungeons_and_dragons"}, {"name": "Kraken", "tag": "kraken", "url": "https://api.thingiverse.com/tags/kraken", "count": 130, "things_url": "https://api.thingiverse.com/tags/kraken/things", "absolute_url": "https://www.thingiverse.com/tag:Kraken"}, {"name": "monster", "tag": "monster", "url": "https://api.thingiverse.com/tags/monster", "count": 2913, "things_url": "https://api.thingiverse.com/tags/monster/things", "absolute_url": "https://www.thingiverse.com/tag:monster"}, {"name": "pathfinder", "tag": "pathfinder", "url": "https://api.thingiverse.com/tags/pathfinder", "count": 4005, "things_url": "https://api.thingiverse.com/tags/pathfinder/things", "absolute_url": "https://www.thingiverse.com/tag:pathfinder"}, {"name": "sea monster", "tag": "sea_monster", "url": "https://api.thingiverse.com/tags/sea_monster", "count": 17, "things_url": "https://api.thingiverse.com/tags/sea_monster/things", "absolute_url": "https://www.thingiverse.com/tag:sea_monster"}, {"name": "seat", "tag": "seat", "url": "https://api.thingiverse.com/tags/seat", "count": 537, "things_url": "https://api.thingiverse.com/tags/seat/things", "absolute_url": "https://www.thingiverse.com/tag:seat"}], "is_nsfw": false}]