[{"id": 3621370, "name": "Orc Axe Beak Rider", "url": "https://api.thingiverse.com/things/3621370", "public_url": "https://www.thingiverse.com/thing:3621370", "created_at": "2019-05-10T16:50:03+00:00", "thumbnail": "https://cdn.thingiverse.com/renders/1b/ca/aa/04/75/b42fc3534dda79e7f762601ad4250aec_display_large.JPG", "preview_image": "https://cdn.thingiverse.com/renders/1b/ca/aa/04/75/b42fc3534dda79e7f762601ad4250aec_preview_card.JPG", "creator": {"id": 325497, "name": "mz4250", "first_name": "Miguel", "last_name": "Zavala", "url": "https://api.thingiverse.com/users/mz4250", "public_url": "https://www.thingiverse.com/mz4250", "thumbnail": "https://cdn.thingiverse.com/renders/7f/80/a3/0a/5e/Manly1_thumb_medium.jpg", "count_of_followers": 18222, "count_of_following": 78, "count_of_designs": 584, "accepts_tips": true, "is_following": false, "location": "", "cover": "https://cdn.thingiverse.com/renders/8a/1e/7f/05/ab/dice2_preview_large.jpg"}, "is_private": null, "is_purchased": null, "is_published": null, "comment_count": 4, "like_count": 215, "tags": [{"name": "axe beak", "tag": "axe_beak", "url": "https://api.thingiverse.com/tags/axe_beak", "count": 3, "things_url": "https://api.thingiverse.com/tags/axe_beak/things", "absolute_url": "https://www.thingiverse.com/tag:axe_beak"}, {"name": "orc", "tag": "orc", "url": "https://api.thingiverse.com/tags/orc", "count": 427, "things_url": "https://api.thingiverse.com/tags/orc/things", "absolute_url": "https://www.thingiverse.com/tag:orc"}], "is_nsfw": false}, {"id": 3621144, "name": "Furniture Collection (So far)", "url": "https://api.thingiverse.com/things/3621144", "public_url": "https://www.thingiverse.com/thing:3621144", "created_at": "2019-05-10T15:33:03+00:00", "thumbnail": "https://cdn.thingiverse.com/site/img/default/Gears_display_large.jpg", "preview_image": "https://cdn.thingiverse.com/site/img/default/Gears_preview_card.jpg", "creator": {"id": 325497, "name": "mz4250", "first_name": "Miguel", "last_name": "Zavala", "url": "https://api.thingiverse.com/users/mz4250", "public_url": "https://www.thingiverse.com/mz4250", "thumbnail": "https://cdn.thingiverse.com/renders/7f/80/a3/0a/5e/Manly1_thumb_medium.jpg", "count_of_followers": 18222, "count_of_following": 78, "count_of_designs": 584, "accepts_tips": true, "is_following": false, "location": "", "cover": "https://cdn.thingiverse.com/renders/8a/1e/7f/05/ab/dice2_preview_large.jpg"}, "is_private": null, "is_purchased": null, "is_published": null, "comment_count": null, "like_count": 124, "tags": [{"name": "piano", "tag": "piano", "url": "https://api.thingiverse.com/tags/piano", "count": 202, "things_url": "https://api.thingiverse.com/tags/piano/things", "absolute_url": "https://www.thingiverse.com/tag:piano"}], "is_nsfw": false}, {"id": 3615119, "name": "Hastur, the King in Yellow", "url": "https://api.thingiverse.com/things/3615119", "public_url": "https://www.thingiverse.com/thing:3615119", "created_at": "2019-05-08T00:08:12+00:00", "thumbnail": "https://cdn.thingiverse.com/renders/17/51/18/2f/ba/3515270e093eae55b810b929a2893653_display_large.JPG", "preview_image": "https://cdn.thingiverse.com/renders/17/51/18/2f/ba/3515270e093eae55b810b929a2893653_preview_card.JPG", "creator": {"id": 325497, "name": "mz4250", "first_name": "Miguel", "last_name": "Zavala", "url": "https://api.thingiverse.com/users/mz4250", "public_url": "https://www.thingiverse.com/mz4250", "thumbnail": "https://cdn.thingiverse.com/renders/7f/80/a3/0a/5e/Manly1_thumb_medium.jpg", "count_of_followers": 18222, "count_of_following": 78, "count_of_designs": 584, "accepts_tips": true, "is_following": false, "location": "", "cover": "https://cdn.thingiverse.com/renders/8a/1e/7f/05/ab/dice2_preview_large.jpg"}, "is_private": null, "is_purchased": null, "is_published": null, "comment_count": 11, "like_count": 391, "tags": [{"name": "lovecraft", "tag": "lovecraft", "url": "https://api.thingiverse.com/tags/lovecraft", "count": 237, "things_url": "https://api.thingiverse.com/tags/lovecraft/things", "absolute_url": "https://www.thingiverse.com/tag:lovecraft"}], "is_nsfw": false}, {"id": 3605048, "name": "Human Cavalier Collection", "url": "https://api.thingiverse.com/things/3605048", "public_url": "https://www.thingiverse.com/thing:3605048", "created_at": "2019-05-03T15:25:14+00:00", "thumbnail": "https://cdn.thingiverse.com/renders/50/c7/54/15/8f/d6832e1b37af7417a1a733e7041efbdb_display_large.JPG", "preview_image": "https://cdn.thingiverse.com/renders/50/c7/54/15/8f/d6832e1b37af7417a1a733e7041efbdb_preview_card.JPG", "creator": {"id": 325497, "name": "mz4250", "first_name": "Miguel", "last_name": "Zavala", "url": "https://api.thingiverse.com/users/mz4250", "public_url": "https://www.thingiverse.com/mz4250", "thumbnail": "https://cdn.thingiverse.com/renders/7f/80/a3/0a/5e/Manly1_thumb_medium.jpg", "count_of_followers": 18222, "count_of_following": 78, "count_of_designs": 584, "accepts_tips": true, "is_following": false, "location": "", "cover": "https://cdn.thingiverse.com/renders/8a/1e/7f/05/ab/dice2_preview_large.jpg"}, "is_private": null, "is_purchased": null, "is_published": null, "comment_count": 12, "like_count": 290, "tags": [{"name": "Cavalier", "tag": "cavalier", "url": "https://api.thingiverse.com/tags/cavalier", "count": 30, "things_url": "https://api.thingiverse.com/tags/cavalier/things", "absolute_url": "https://www.thingiverse.com/tag:Cavalier"}, {"name": "dd", "tag": "dd", "url": "https://api.thingiverse.com/tags/dd", "count": 1, "things_url": "https://api.thingiverse.com/tags/dd/things", "absolute_url": "https://www.thingiverse.com/tag:dd"}, {"name": "dnd", "tag": "dnd", "url": "https://api.thingiverse.com/tags/dnd", "count": 11070, "things_url": "https://api.thingiverse.com/tags/dnd/things", "absolute_url": "https://www.thingiverse.com/tag:dnd"}, {"name": "knight", "tag": "knight", "url": "https://api.thingiverse.com/tags/knight", "count": 919, "things_url": "https://api.thingiverse.com/tags/knight/things", "absolute_url": "https://www.thingiverse.com/tag:knight"}, {"name": "pathfinder", "tag": "pathfinder", "url": "https://api.thingiverse.com/tags/pathfinder", "count": 4005, "things_url": "https://api.thingiverse.com/tags/pathfinder/things", "absolute_url": "https://www.thingiverse.com/tag:pathfinder"}], "is_nsfw": false}, {"id": 3589436, "name": "Prawnfolk", "url": "https://api.thingiverse.com/things/3589436", "public_url": "https://www.thingiverse.com/thing:3589436", "created_at": "2019-04-26T13:35:21+00:00", "thumbnail": "https://cdn.thingiverse.com/renders/30/1e/9b/c1/a0/f1fb4cf0f9fb301d0e7b6659196e108f_display_large.JPG", "preview_image": "https://cdn.thingiverse.com/renders/30/1e/9b/c1/a0/f1fb4cf0f9fb301d0e7b6659196e108f_preview_card.JPG", "creator": {"id": 325497, "name": "mz4250", "first_name": "Miguel", "last_name": "Zavala", "url": "https://api.thingiverse.com/users/mz4250", "public_url": "https://www.thingiverse.com/mz4250", "thumbnail": "https://cdn.thingiverse.com/renders/7f/80/a3/0a/5e/Manly1_thumb_medium.jpg", "count_of_followers": 18222, "count_of_following": 78, "count_of_designs": 584, "accepts_tips": true, "is_following": false, "location": "", "cover": "https://cdn.thingiverse.com/renders/8a/1e/7f/05/ab/dice2_preview_large.jpg"}, "is_private": null, "is_purchased": null, "is_published": null, "comment_count": null, "like_count": 107, "tags": [{"name": "lobsterfolk", "tag": "lobsterfolk", "url": "https://api.thingiverse.com/tags/lobsterfolk", "count": 1, "things_url": "https://api.thingiverse.com/tags/lobsterfolk/things", "absolute_url": "https://www.thingiverse.com/tag:lobsterfolk"}, {"name": "prawn", "tag": "prawn", "url": "https://api.thingiverse.com/tags/prawn", "count": 7, "things_url": "https://api.thingiverse.com/tags/prawn/things", "absolute_url": "https://www.thingiverse.com/tag:prawn"}, {"name": "prawnfolk", "tag": "prawnfolk", "url": "https://api.thingiverse.com/tags/prawnfolk", "count": 1, "things_url": "https://api.thingiverse.com/tags/prawnfolk/things", "absolute_url": "https://www.thingiverse.com/tag:prawnfolk"}], "is_nsfw": false}, {"id": 3589348, "name": "Fat Noble", "url": "https://api.thingiverse.com/things/3589348", "public_url": "https://www.thingiverse.com/thing:3589348", "created_at": "2019-04-26T12:29:05+00:00", "thumbnail": "https://cdn.thingiverse.com/renders/3b/48/a9/ac/72/36e6f4355fcf6a22c9ad68feee39f68f_display_large.JPG", "preview_image": "https://cdn.thingiverse.com/renders/3b/48/a9/ac/72/36e6f4355fcf6a22c9ad68feee39f68f_preview_card.JPG", "creator": {"id": 325497, "name": "mz4250", "first_name": "Miguel", "last_name": "Zavala", "url": "https://api.thingiverse.com/users/mz4250", "public_url": "https://www.thingiverse.com/mz4250", "thumbnail": "https://cdn.thingiverse.com/renders/7f/80/a3/0a/5e/Manly1_thumb_medium.jpg", "count_of_followers": 18222, "count_of_following": 78, "count_of_designs": 584, "accepts_tips": true, "is_following": false, "location": "", "cover": "https://cdn.thingiverse.com/renders/8a/1e/7f/05/ab/dice2_preview_large.jpg"}, "is_private": null, "is_purchased": null, "is_published": null, "comment_count": 4, "like_count": 125, "tags": [{"name": "dnd", "tag": "dnd", "url": "https://api.thingiverse.com/tags/dnd", "count": 11070, "things_url": "https://api.thingiverse.com/tags/dnd/things", "absolute_url": "https://www.thingiverse.com/tag:dnd"}, {"name": "Fat", "tag": "fat", "url": "https://api.thingiverse.com/tags/fat", "count": 119, "things_url": "https://api.thingiverse.com/tags/fat/things", "absolute_url": "https://www.thingiverse.com/tag:Fat"}, {"name": "fluffy", "tag": "fluffy", "url": "https://api.thingiverse.com/tags/fluffy", "count": 22, "things_url": "https://api.thingiverse.com/tags/fluffy/things", "absolute_url": "https://www.thingiverse.com/tag:fluffy"}, {"name": "king", "tag": "king", "url": "https://api.thingiverse.com/tags/king", "count": 442, "things_url": "https://api.thingiverse.com/tags/king/things", "absolute_url": "https://www.thingiverse.com/tag:king"}, {"name": "lord", "tag": "lord", "url": "https://api.thingiverse.com/tags/lord", "count": 73, "things_url": "https://api.thingiverse.com/tags/lord/things", "absolute_url": "https://www.thingiverse.com/tag:lord"}, {"name": "Noble", "tag": "noble", "url": "https://api.thingiverse.com/tags/noble", "count": 71, "things_url": "https://api.thingiverse.com/tags/noble/things", "absolute_url": "https://www.thingiverse.com/tag:Noble"}], "is_nsfw": false}, {"id": 3577815, "name": "Agnibarrra", "url": "https://api.thingiverse.com/things/3577815", "public_url": "https://www.thingiverse.com/thing:3577815", "created_at": "2019-04-21T02:41:13+00:00", "thumbnail": "https://cdn.thingiverse.com/renders/f0/50/14/c1/b2/4b27c4aad0904542bcb6d81c8e762a48_display_large.jpg", "preview_image": "https://cdn.thingiverse.com/renders/f0/50/14/c1/b2/4b27c4aad0904542bcb6d81c8e762a48_preview_card.jpg", "creator": {"id": 325497, "name": "mz4250", "first_name": "Miguel", "last_name": "Zavala", "url": "https://api.thingiverse.com/users/mz4250", "public_url": "https://www.thingiverse.com/mz4250", "thumbnail": "https://cdn.thingiverse.com/renders/7f/80/a3/0a/5e/Manly1_thumb_medium.jpg", "count_of_followers": 18222, "count_of_following": 78, "count_of_designs": 584, "accepts_tips": true, "is_following": false, "location": "", "cover": "https://cdn.thingiverse.com/renders/8a/1e/7f/05/ab/dice2_preview_large.jpg"}, "is_private": null, "is_purchased": null, "is_published": null, "comment_count": null, "like_count": 105, "tags": [{"name": "dnd", "tag": "dnd", "url": "https://api.thingiverse.com/tags/dnd", "count": 11070, "things_url": "https://api.thingiverse.com/tags/dnd/things", "absolute_url": "https://www.thingiverse.com/tag:dnd"}, {"name": "elemental", "tag": "elemental", "url": "https://api.thingiverse.com/tags/elemental", "count": 170, "things_url": "https://api.thingiverse.com/tags/elemental/things", "absolute_url": "https://www.thingiverse.com/tag:elemental"}], "is_nsfw": false}, {"id": 3577412, "name": "Morko", "url": "https://api.thingiverse.com/things/3577412", "public_url": "https://www.thingiverse.com/thing:3577412", "created_at": "2019-04-20T21:14:29+00:00", "thumbnail": "https://cdn.thingiverse.com/renders/53/6e/76/eb/c1/ea90345517db5f8a1ffc446416e2058f_display_large.jpg", "preview_image": "https://cdn.thingiverse.com/renders/53/6e/76/eb/c1/ea90345517db5f8a1ffc446416e2058f_preview_card.jpg", "creator": {"id": 325497, "name": "mz4250", "first_name": "Miguel", "last_name": "Zavala", "url": "https://api.thingiverse.com/users/mz4250", "public_url": "https://www.thingiverse.com/mz4250", "thumbnail": "https://cdn.thingiverse.com/renders/7f/80/a3/0a/5e/Manly1_thumb_medium.jpg", "count_of_followers": 18222, "count_of_following": 78, "count_of_designs": 584, "accepts_tips": true, "is_following": false, "location": "", "cover": "https://cdn.thingiverse.com/renders/8a/1e/7f/05/ab/dice2_preview_large.jpg"}, "is_private": null, "is_purchased": null, "is_published": null, "comment_count": null, "like_count": 69, "tags": [{"name": "creature codex", "tag": "creature_codex", "url": "https://api.thingiverse.com/tags/creature_codex", "count": 3, "things_url": "https://api.thingiverse.com/tags/creature_codex/things", "absolute_url": "https://www.thingiverse.com/tag:creature_codex"}, {"name": "dnd", "tag": "dnd", "url": "https://api.thingiverse.com/tags/dnd", "count": 11070, "things_url": "https://api.thingiverse.com/tags/dnd/things", "absolute_url": "https://www.thingiverse.com/tag:dnd"}, {"name": "kobold press", "tag": "kobold_press", "url": "https://api.thingiverse.com/tags/kobold_press", "count": 13, "things_url": "https://api.thingiverse.com/tags/kobold_press/things", "absolute_url": "https://www.thingiverse.com/tag:kobold_press"}], "is_nsfw": false}, {"id": 3576661, "name": "Arcanaphage", "url": "https://api.thingiverse.com/things/3576661", "public_url": "https://www.thingiverse.com/thing:3576661", "created_at": "2019-04-20T13:34:50+00:00", "thumbnail": "https://cdn.thingiverse.com/renders/cc/30/b5/c8/79/ced4e916f229faf21cb13447648486a8_display_large.jpg", "preview_image": "https://cdn.thingiverse.com/renders/cc/30/b5/c8/79/ced4e916f229faf21cb13447648486a8_preview_card.jpg", "creator": {"id": 325497, "name": "mz4250", "first_name": "Miguel", "last_name": "Zavala", "url": "https://api.thingiverse.com/users/mz4250", "public_url": "https://www.thingiverse.com/mz4250", "thumbnail": "https://cdn.thingiverse.com/renders/7f/80/a3/0a/5e/Manly1_thumb_medium.jpg", "count_of_followers": 18222, "count_of_following": 78, "count_of_designs": 584, "accepts_tips": true, "is_following": false, "location": "", "cover": "https://cdn.thingiverse.com/renders/8a/1e/7f/05/ab/dice2_preview_large.jpg"}, "is_private": null, "is_purchased": null, "is_published": null, "comment_count": 2, "like_count": 85, "tags": [{"name": "dnd", "tag": "dnd", "url": "https://api.thingiverse.com/tags/dnd", "count": 11070, "things_url": "https://api.thingiverse.com/tags/dnd/things", "absolute_url": "https://www.thingiverse.com/tag:dnd"}, {"name": "dnd miniature", "tag": "dnd_miniature", "url": "https://api.thingiverse.com/tags/dnd_miniature", "count": 3775, "things_url": "https://api.thingiverse.com/tags/dnd_miniature/things", "absolute_url": "https://www.thingiverse.com/tag:dnd_miniature"}, {"name": "kobold press", "tag": "kobold_press", "url": "https://api.thingiverse.com/tags/kobold_press", "count": 13, "things_url": "https://api.thingiverse.com/tags/kobold_press/things", "absolute_url": "https://www.thingiverse.com/tag:kobold_press"}], "is_nsfw": false}, {"id": 3573704, "name": "Drow Collection", "url": "https://api.thingiverse.com/things/3573704", "public_url": "https://www.thingiverse.com/thing:3573704", "created_at": "2019-04-19T02:37:34+00:00", "thumbnail": "https://cdn.thingiverse.com/renders/24/9b/5e/eb/68/e10fcb2373811428767ca87f6a3392c0_display_large.JPG", "preview_image": "https://cdn.thingiverse.com/renders/24/9b/5e/eb/68/e10fcb2373811428767ca87f6a3392c0_preview_card.JPG", "creator": {"id": 325497, "name": "mz4250", "first_name": "Miguel", "last_name": "Zavala", "url": "https://api.thingiverse.com/users/mz4250", "public_url": "https://www.thingiverse.com/mz4250", "thumbnail": "https://cdn.thingiverse.com/renders/7f/80/a3/0a/5e/Manly1_thumb_medium.jpg", "count_of_followers": 18222, "count_of_following": 78, "count_of_designs": 584, "accepts_tips": true, "is_following": false, "location": "", "cover": "https://cdn.thingiverse.com/renders/8a/1e/7f/05/ab/dice2_preview_large.jpg"}, "is_private": null, "is_purchased": null, "is_published": null, "comment_count": 3, "like_count": 734, "tags": [{"name": "dd", "tag": "dd", "url": "https://api.thingiverse.com/tags/dd", "count": 1, "things_url": "https://api.thingiverse.com/tags/dd/things", "absolute_url": "https://www.thingiverse.com/tag:dd"}, {"name": "dnd", "tag": "dnd", "url": "https://api.thingiverse.com/tags/dnd", "count": 11070, "things_url": "https://api.thingiverse.com/tags/dnd/things", "absolute_url": "https://www.thingiverse.com/tag:dnd"}, {"name": "drow", "tag": "drow", "url": "https://api.thingiverse.com/tags/drow", "count": 46, "things_url": "https://api.thingiverse.com/tags/drow/things", "absolute_url": "https://www.thingiverse.com/tag:drow"}, {"name": "dungeons and dragons", "tag": "dungeons_and_dragons", "url": "https://api.thingiverse.com/tags/dungeons_and_dragons", "count": 8466, "things_url": "https://api.thingiverse.com/tags/dungeons_and_dragons/things", "absolute_url": "https://www.thingiverse.com/tag:dungeons_and_dragons"}, {"name": "Elf", "tag": "elf", "url": "https://api.thingiverse.com/tags/elf", "count": 551, "things_url": "https://api.thingiverse.com/tags/elf/things", "absolute_url": "https://www.thingiverse.com/tag:Elf"}, {"name": "mage", "tag": "mage", "url": "https://api.thingiverse.com/tags/mage", "count": 316, "things_url": "https://api.thingiverse.com/tags/mage/things", "absolute_url": "https://www.thingiverse.com/tag:mage"}], "is_nsfw": false}, {"id": 3573703, "name": "Sea Hag's Creeping Hut", "url": "https://api.thingiverse.com/things/3573703", "public_url": "https://www.thingiverse.com/thing:3573703", "created_at": "2019-04-19T02:37:22+00:00", "thumbnail": "https://cdn.thingiverse.com/renders/ff/c7/e8/cd/c0/6560740e68be6edd458c47da3ceceac5_display_large.JPG", "preview_image": "https://cdn.thingiverse.com/renders/ff/c7/e8/cd/c0/6560740e68be6edd458c47da3ceceac5_preview_card.JPG", "creator": {"id": 325497, "name": "mz4250", "first_name": "Miguel", "last_name": "Zavala", "url": "https://api.thingiverse.com/users/mz4250", "public_url": "https://www.thingiverse.com/mz4250", "thumbnail": "https://cdn.thingiverse.com/renders/7f/80/a3/0a/5e/Manly1_thumb_medium.jpg", "count_of_followers": 18222, "count_of_following": 78, "count_of_designs": 584, "accepts_tips": true, "is_following": false, "location": "", "cover": "https://cdn.thingiverse.com/renders/8a/1e/7f/05/ab/dice2_preview_large.jpg"}, "is_private": null, "is_purchased": null, "is_published": null, "comment_count": 6, "like_count": 174, "tags": [{"name": "dd", "tag": "dd", "url": "https://api.thingiverse.com/tags/dd", "count": 1, "things_url": "https://api.thingiverse.com/tags/dd/things", "absolute_url": "https://www.thingiverse.com/tag:dd"}, {"name": "dnd", "tag": "dnd", "url": "https://api.thingiverse.com/tags/dnd", "count": 11070, "things_url": "https://api.thingiverse.com/tags/dnd/things", "absolute_url": "https://www.thingiverse.com/tag:dnd"}, {"name": "hag", "tag": "hag", "url": "https://api.thingiverse.com/tags/hag", "count": 17, "things_url": "https://api.thingiverse.com/tags/hag/things", "absolute_url": "https://www.thingiverse.com/tag:hag"}, {"name": "Hut", "tag": "hut", "url": "https://api.thingiverse.com/tags/hut", "count": 79, "things_url": "https://api.thingiverse.com/tags/hut/things", "absolute_url": "https://www.thingiverse.com/tag:Hut"}, {"name": "ocean", "tag": "ocean", "url": "https://api.thingiverse.com/tags/ocean", "count": 345, "things_url": "https://api.thingiverse.com/tags/ocean/things", "absolute_url": "https://www.thingiverse.com/tag:ocean"}, {"name": "pathfinder", "tag": "pathfinder", "url": "https://api.thingiverse.com/tags/pathfinder", "count": 4005, "things_url": "https://api.thingiverse.com/tags/pathfinder/things", "absolute_url": "https://www.thingiverse.com/tag:pathfinder"}, {"name": "sea", "tag": "sea", "url": "https://api.thingiverse.com/tags/sea", "count": 516, "things_url": "https://api.thingiverse.com/tags/sea/things", "absolute_url": "https://www.thingiverse.com/tag:sea"}, {"name": "sea hag", "tag": "sea_hag", "url": "https://api.thingiverse.com/tags/sea_hag", "count": 4, "things_url": "https://api.thingiverse.com/tags/sea_hag/things", "absolute_url": "https://www.thingiverse.com/tag:sea_hag"}, {"name": "witch", "tag": "witch", "url": "https://api.thingiverse.com/tags/witch", "count": 290, "things_url": "https://api.thingiverse.com/tags/witch/things", "absolute_url": "https://www.thingiverse.com/tag:witch"}], "is_nsfw": false}, {"id": 3566630, "name": "Rubber Ducky Landing Craft for 8 PCs", "url": "https://api.thingiverse.com/things/3566630", "public_url": "https://www.thingiverse.com/thing:3566630", "created_at": "2019-04-15T20:54:57+00:00", "thumbnail": "https://cdn.thingiverse.com/renders/49/6f/a0/e1/02/9f5c3b556434771c857a4f6b366b0477_display_large.JPG", "preview_image": "https://cdn.thingiverse.com/renders/49/6f/a0/e1/02/9f5c3b556434771c857a4f6b366b0477_preview_card.JPG", "creator": {"id": 325497, "name": "mz4250", "first_name": "Miguel", "last_name": "Zavala", "url": "https://api.thingiverse.com/users/mz4250", "public_url": "https://www.thingiverse.com/mz4250", "thumbnail": "https://cdn.thingiverse.com/renders/7f/80/a3/0a/5e/Manly1_thumb_medium.jpg", "count_of_followers": 18222, "count_of_following": 78, "count_of_designs": 584, "accepts_tips": true, "is_following": false, "location": "", "cover": "https://cdn.thingiverse.com/renders/8a/1e/7f/05/ab/dice2_preview_large.jpg"}, "is_private": null, "is_purchased": null, "is_published": null, "comment_count": 2, "like_count": 94, "tags": [{"name": "dnd", "tag": "dnd", "url": "https://api.thingiverse.com/tags/dnd", "count": 11070, "things_url": "https://api.thingiverse.com/tags/dnd/things", "absolute_url": "https://www.thingiverse.com/tag:dnd"}, {"name": "Ducky", "tag": "ducky", "url": "https://api.thingiverse.com/tags/ducky", "count": 72, "things_url": "https://api.thingiverse.com/tags/ducky/things", "absolute_url": "https://www.thingiverse.com/tag:Ducky"}, {"name": "landing craft", "tag": "landing_craft", "url": "https://api.thingiverse.com/tags/landing_craft", "count": 3, "things_url": "https://api.thingiverse.com/tags/landing_craft/things", "absolute_url": "https://www.thingiverse.com/tag:landing_craft"}, {"name": "Rubber Ducky", "tag": "rubber_ducky", "url": "https://api.thingiverse.com/tags/rubber_ducky", "count": 62, "things_url": "https://api.thingiverse.com/tags/rubber_ducky/things", "absolute_url": "https://www.thingiverse.com/tag:Rubber_Ducky"}], "is_nsfw": false}, {"id": 3565539, "name": "Beer Barrel Golem", "url": "https://api.thingiverse.com/things/3565539", "public_url": "https://www.thingiverse.com/thing:3565539", "created_at": "2019-04-15T11:30:51+00:00", "thumbnail": "https://cdn.thingiverse.com/renders/8f/b9/25/67/33/380eeb95d4ac91f3a45f13902de9f9cf_display_large.jpg", "preview_image": "https://cdn.thingiverse.com/renders/8f/b9/25/67/33/380eeb95d4ac91f3a45f13902de9f9cf_preview_card.jpg", "creator": {"id": 325497, "name": "mz4250", "first_name": "Miguel", "last_name": "Zavala", "url": "https://api.thingiverse.com/users/mz4250", "public_url": "https://www.thingiverse.com/mz4250", "thumbnail": "https://cdn.thingiverse.com/renders/7f/80/a3/0a/5e/Manly1_thumb_medium.jpg", "count_of_followers": 18222, "count_of_following": 78, "count_of_designs": 584, "accepts_tips": true, "is_following": false, "location": "", "cover": "https://cdn.thingiverse.com/renders/8a/1e/7f/05/ab/dice2_preview_large.jpg"}, "is_private": null, "is_purchased": null, "is_published": null, "comment_count": 12, "like_count": 427, "tags": [{"name": "barrel", "tag": "barrel", "url": "https://api.thingiverse.com/tags/barrel", "count": 676, "things_url": "https://api.thingiverse.com/tags/barrel/things", "absolute_url": "https://www.thingiverse.com/tag:barrel"}, {"name": "beer", "tag": "beer", "url": "https://api.thingiverse.com/tags/beer", "count": 1672, "things_url": "https://api.thingiverse.com/tags/beer/things", "absolute_url": "https://www.thingiverse.com/tag:beer"}, {"name": "dnd", "tag": "dnd", "url": "https://api.thingiverse.com/tags/dnd", "count": 11070, "things_url": "https://api.thingiverse.com/tags/dnd/things", "absolute_url": "https://www.thingiverse.com/tag:dnd"}, {"name": "golem", "tag": "golem", "url": "https://api.thingiverse.com/tags/golem", "count": 153, "things_url": "https://api.thingiverse.com/tags/golem/things", "absolute_url": "https://www.thingiverse.com/tag:golem"}, {"name": "robot", "tag": "robot", "url": "https://api.thingiverse.com/tags/robot", "count": 6505, "things_url": "https://api.thingiverse.com/tags/robot/things", "absolute_url": "https://www.thingiverse.com/tag:robot"}], "is_nsfw": false}, {"id": 3548066, "name": "Fungal Zombie", "url": "https://api.thingiverse.com/things/3548066", "public_url": "https://www.thingiverse.com/thing:3548066", "created_at": "2019-04-07T20:21:23+00:00", "thumbnail": "https://cdn.thingiverse.com/renders/17/6e/fd/31/80/b52914379d43b0d05338a5df608f98a0_display_large.JPG", "preview_image": "https://cdn.thingiverse.com/renders/17/6e/fd/31/80/b52914379d43b0d05338a5df608f98a0_preview_card.JPG", "creator": {"id": 325497, "name": "mz4250", "first_name": "Miguel", "last_name": "Zavala", "url": "https://api.thingiverse.com/users/mz4250", "public_url": "https://www.thingiverse.com/mz4250", "thumbnail": "https://cdn.thingiverse.com/renders/7f/80/a3/0a/5e/Manly1_thumb_medium.jpg", "count_of_followers": 18222, "count_of_following": 78, "count_of_designs": 584, "accepts_tips": true, "is_following": false, "location": "", "cover": "https://cdn.thingiverse.com/renders/8a/1e/7f/05/ab/dice2_preview_large.jpg"}, "is_private": null, "is_purchased": null, "is_published": null, "comment_count": 6, "like_count": 269, "tags": [{"name": "dnd", "tag": "dnd", "url": "https://api.thingiverse.com/tags/dnd", "count": 11070, "things_url": "https://api.thingiverse.com/tags/dnd/things", "absolute_url": "https://www.thingiverse.com/tag:dnd"}, {"name": "fungal", "tag": "fungal", "url": "https://api.thingiverse.com/tags/fungal", "count": 5, "things_url": "https://api.thingiverse.com/tags/fungal/things", "absolute_url": "https://www.thingiverse.com/tag:fungal"}, {"name": "fungi", "tag": "fungi", "url": "https://api.thingiverse.com/tags/fungi", "count": 37, "things_url": "https://api.thingiverse.com/tags/fungi/things", "absolute_url": "https://www.thingiverse.com/tag:fungi"}, {"name": "shroom", "tag": "shroom", "url": "https://api.thingiverse.com/tags/shroom", "count": 26, "things_url": "https://api.thingiverse.com/tags/shroom/things", "absolute_url": "https://www.thingiverse.com/tag:shroom"}, {"name": "zombie", "tag": "zombie", "url": "https://api.thingiverse.com/tags/zombie", "count": 575, "things_url": "https://api.thingiverse.com/tags/zombie/things", "absolute_url": "https://www.thingiverse.com/tag:zombie"}], "is_nsfw": false}, {"id": 3530506, "name": "Female Ranger and her Giant Panther Mount", "url": "https://api.thingiverse.com/things/3530506", "public_url": "https://www.thingiverse.com/thing:3530506", "created_at": "2019-03-31T12:28:40+00:00", "thumbnail": "https://cdn.thingiverse.com/renders/82/7e/3f/9d/5f/f6d8f693deb9c55f00a0af248562b165_display_large.jpg", "preview_image": "https://cdn.thingiverse.com/renders/82/7e/3f/9d/5f/f6d8f693deb9c55f00a0af248562b165_preview_card.jpg", "creator": {"id": 325497, "name": "mz4250", "first_name": "Miguel", "last_name": "Zavala", "url": "https://api.thingiverse.com/users/mz4250", "public_url": "https://www.thingiverse.com/mz4250", "thumbnail": "https://cdn.thingiverse.com/renders/7f/80/a3/0a/5e/Manly1_thumb_medium.jpg", "count_of_followers": 18222, "count_of_following": 78, "count_of_designs": 584, "accepts_tips": true, "is_following": false, "location": "", "cover": "https://cdn.thingiverse.com/renders/8a/1e/7f/05/ab/dice2_preview_large.jpg"}, "is_private": null, "is_purchased": null, "is_published": null, "comment_count": null, "like_count": 283, "tags": [{"name": "dd", "tag": "dd", "url": "https://api.thingiverse.com/tags/dd", "count": 1, "things_url": "https://api.thingiverse.com/tags/dd/things", "absolute_url": "https://www.thingiverse.com/tag:dd"}, {"name": "dnd", "tag": "dnd", "url": "https://api.thingiverse.com/tags/dnd", "count": 11070, "things_url": "https://api.thingiverse.com/tags/dnd/things", "absolute_url": "https://www.thingiverse.com/tag:dnd"}, {"name": "mount", "tag": "mount", "url": "https://api.thingiverse.com/tags/mount", "count": 18649, "things_url": "https://api.thingiverse.com/tags/mount/things", "absolute_url": "https://www.thingiverse.com/tag:mount"}, {"name": "panther", "tag": "panther", "url": "https://api.thingiverse.com/tags/panther", "count": 105, "things_url": "https://api.thingiverse.com/tags/panther/things", "absolute_url": "https://www.thingiverse.com/tag:panther"}, {"name": "ranger", "tag": "ranger", "url": "https://api.thingiverse.com/tags/ranger", "count": 290, "things_url": "https://api.thingiverse.com/tags/ranger/things", "absolute_url": "https://www.thingiverse.com/tag:ranger"}, {"name": "reprap", "tag": "reprap", "url": "https://api.thingiverse.com/tags/reprap", "count": 4416, "things_url": "https://api.thingiverse.com/tags/reprap/things", "absolute_url": "https://www.thingiverse.com/tag:reprap"}], "is_nsfw": false}, {"id": 3512950, "name": "The Leviathan", "url": "https://api.thingiverse.com/things/3512950", "public_url": "https://www.thingiverse.com/thing:3512950", "created_at": "2019-03-23T22:27:33+00:00", "thumbnail": "https://cdn.thingiverse.com/renders/f3/17/f1/f0/13/c663a328147b4f7fdc85878ab2f8b332_display_large.jpg", "preview_image": "https://cdn.thingiverse.com/renders/f3/17/f1/f0/13/c663a328147b4f7fdc85878ab2f8b332_preview_card.jpg", "creator": {"id": 325497, "name": "mz4250", "first_name": "Miguel", "last_name": "Zavala", "url": "https://api.thingiverse.com/users/mz4250", "public_url": "https://www.thingiverse.com/mz4250", "thumbnail": "https://cdn.thingiverse.com/renders/7f/80/a3/0a/5e/Manly1_thumb_medium.jpg", "count_of_followers": 18222, "count_of_following": 78, "count_of_designs": 584, "accepts_tips": true, "is_following": false, "location": "", "cover": "https://cdn.thingiverse.com/renders/8a/1e/7f/05/ab/dice2_preview_large.jpg"}, "is_private": null, "is_purchased": null, "is_published": null, "comment_count": null, "like_count": 195, "tags": [{"name": "dnd", "tag": "dnd", "url": "https://api.thingiverse.com/tags/dnd", "count": 11070, "things_url": "https://api.thingiverse.com/tags/dnd/things", "absolute_url": "https://www.thingiverse.com/tag:dnd"}, {"name": "Leviathan", "tag": "leviathan", "url": "https://api.thingiverse.com/tags/leviathan", "count": 90, "things_url": "https://api.thingiverse.com/tags/leviathan/things", "absolute_url": "https://www.thingiverse.com/tag:Leviathan"}, {"name": "sea monster", "tag": "sea_monster", "url": "https://api.thingiverse.com/tags/sea_monster", "count": 17, "things_url": "https://api.thingiverse.com/tags/sea_monster/things", "absolute_url": "https://www.thingiverse.com/tag:sea_monster"}], "is_nsfw": false}, {"id": 3510735, "name": "Gug from Tome of Beasts!", "url": "https://api.thingiverse.com/things/3510735", "public_url": "https://www.thingiverse.com/thing:3510735", "created_at": "2019-03-22T21:16:50+00:00", "thumbnail": "https://cdn.thingiverse.com/renders/d0/2c/5e/11/48/af14446152ddfb3be5c8b62c28ad85ec_display_large.JPG", "preview_image": "https://cdn.thingiverse.com/renders/d0/2c/5e/11/48/af14446152ddfb3be5c8b62c28ad85ec_preview_card.JPG", "creator": {"id": 325497, "name": "mz4250", "first_name": "Miguel", "last_name": "Zavala", "url": "https://api.thingiverse.com/users/mz4250", "public_url": "https://www.thingiverse.com/mz4250", "thumbnail": "https://cdn.thingiverse.com/renders/7f/80/a3/0a/5e/Manly1_thumb_medium.jpg", "count_of_followers": 18222, "count_of_following": 78, "count_of_designs": 584, "accepts_tips": true, "is_following": false, "location": "", "cover": "https://cdn.thingiverse.com/renders/8a/1e/7f/05/ab/dice2_preview_large.jpg"}, "is_private": null, "is_purchased": null, "is_published": null, "comment_count": 4, "like_count": 172, "tags": [{"name": "dnd", "tag": "dnd", "url": "https://api.thingiverse.com/tags/dnd", "count": 11070, "things_url": "https://api.thingiverse.com/tags/dnd/things", "absolute_url": "https://www.thingiverse.com/tag:dnd"}, {"name": "gug", "tag": "gug", "url": "https://api.thingiverse.com/tags/gug", "count": 6, "things_url": "https://api.thingiverse.com/tags/gug/things", "absolute_url": "https://www.thingiverse.com/tag:gug"}, {"name": "tome of beasts", "tag": "tome_of_beasts", "url": "https://api.thingiverse.com/tags/tome_of_beasts", "count": 7, "things_url": "https://api.thingiverse.com/tags/tome_of_beasts/things", "absolute_url": "https://www.thingiverse.com/tag:tome_of_beasts"}], "is_nsfw": false}, {"id": 3510524, "name": "Halfling Cavalier on an Armored Gorilla!  ", "url": "https://api.thingiverse.com/things/3510524", "public_url": "https://www.thingiverse.com/thing:3510524", "created_at": "2019-03-22T19:27:47+00:00", "thumbnail": "https://cdn.thingiverse.com/renders/48/99/61/13/e5/8043405cc64f53e58269479228e86155_display_large.JPG", "preview_image": "https://cdn.thingiverse.com/renders/48/99/61/13/e5/8043405cc64f53e58269479228e86155_preview_card.JPG", "creator": {"id": 325497, "name": "mz4250", "first_name": "Miguel", "last_name": "Zavala", "url": "https://api.thingiverse.com/users/mz4250", "public_url": "https://www.thingiverse.com/mz4250", "thumbnail": "https://cdn.thingiverse.com/renders/7f/80/a3/0a/5e/Manly1_thumb_medium.jpg", "count_of_followers": 18222, "count_of_following": 78, "count_of_designs": 584, "accepts_tips": true, "is_following": false, "location": "", "cover": "https://cdn.thingiverse.com/renders/8a/1e/7f/05/ab/dice2_preview_large.jpg"}, "is_private": null, "is_purchased": null, "is_published": null, "comment_count": 2, "like_count": 189, "tags": [{"name": "dnd", "tag": "dnd", "url": "https://api.thingiverse.com/tags/dnd", "count": 11070, "things_url": "https://api.thingiverse.com/tags/dnd/things", "absolute_url": "https://www.thingiverse.com/tag:dnd"}, {"name": "Gorilla", "tag": "gorilla", "url": "https://api.thingiverse.com/tags/gorilla", "count": 136, "things_url": "https://api.thingiverse.com/tags/gorilla/things", "absolute_url": "https://www.thingiverse.com/tag:Gorilla"}, {"name": "halfling", "tag": "halfling", "url": "https://api.thingiverse.com/tags/halfling", "count": 107, "things_url": "https://api.thingiverse.com/tags/halfling/things", "absolute_url": "https://www.thingiverse.com/tag:halfling"}, {"name": "hobbit", "tag": "hobbit", "url": "https://api.thingiverse.com/tags/hobbit", "count": 137, "things_url": "https://api.thingiverse.com/tags/hobbit/things", "absolute_url": "https://www.thingiverse.com/tag:hobbit"}], "is_nsfw": false}, {"id": 3510292, "name": "Goblin Metalhead", "url": "https://api.thingiverse.com/things/3510292", "public_url": "https://www.thingiverse.com/thing:3510292", "created_at": "2019-03-22T18:01:03+00:00", "thumbnail": "https://cdn.thingiverse.com/renders/40/fd/24/85/b9/7e4f4c85470a67a68c1702033799d54f_display_large.JPG", "preview_image": "https://cdn.thingiverse.com/renders/40/fd/24/85/b9/7e4f4c85470a67a68c1702033799d54f_preview_card.JPG", "creator": {"id": 325497, "name": "mz4250", "first_name": "Miguel", "last_name": "Zavala", "url": "https://api.thingiverse.com/users/mz4250", "public_url": "https://www.thingiverse.com/mz4250", "thumbnail": "https://cdn.thingiverse.com/renders/7f/80/a3/0a/5e/Manly1_thumb_medium.jpg", "count_of_followers": 18222, "count_of_following": 78, "count_of_designs": 584, "accepts_tips": true, "is_following": false, "location": "", "cover": "https://cdn.thingiverse.com/renders/8a/1e/7f/05/ab/dice2_preview_large.jpg"}, "is_private": null, "is_purchased": null, "is_published": null, "comment_count": 10, "like_count": 225, "tags": [{"name": "Bard", "tag": "bard", "url": "https://api.thingiverse.com/tags/bard", "count": 127, "things_url": "https://api.thingiverse.com/tags/bard/things", "absolute_url": "https://www.thingiverse.com/tag:Bard"}, {"name": "goblin", "tag": "goblin", "url": "https://api.thingiverse.com/tags/goblin", "count": 465, "things_url": "https://api.thingiverse.com/tags/goblin/things", "absolute_url": "https://www.thingiverse.com/tag:goblin"}, {"name": "metal", "tag": "metal", "url": "https://api.thingiverse.com/tags/metal", "count": 675, "things_url": "https://api.thingiverse.com/tags/metal/things", "absolute_url": "https://www.thingiverse.com/tag:metal"}, {"name": "Metalhead", "tag": "metalhead", "url": "https://api.thingiverse.com/tags/metalhead", "count": 6, "things_url": "https://api.thingiverse.com/tags/metalhead/things", "absolute_url": "https://www.thingiverse.com/tag:Metalhead"}, {"name": "rocker", "tag": "rocker", "url": "https://api.thingiverse.com/tags/rocker", "count": 70, "things_url": "https://api.thingiverse.com/tags/rocker/things", "absolute_url": "https://www.thingiverse.com/tag:rocker"}], "is_nsfw": false}, {"id": 3510108, "name": "Giant Chicken Mounts!", "url": "https://api.thingiverse.com/things/3510108", "public_url": "https://www.thingiverse.com/thing:3510108", "created_at": "2019-03-22T16:23:57+00:00", "thumbnail": "https://cdn.thingiverse.com/renders/7b/b8/b7/41/c9/6969c41f548f551d01e7c6337628f76d_display_large.JPG", "preview_image": "https://cdn.thingiverse.com/renders/7b/b8/b7/41/c9/6969c41f548f551d01e7c6337628f76d_preview_card.JPG", "creator": {"id": 325497, "name": "mz4250", "first_name": "Miguel", "last_name": "Zavala", "url": "https://api.thingiverse.com/users/mz4250", "public_url": "https://www.thingiverse.com/mz4250", "thumbnail": "https://cdn.thingiverse.com/renders/7f/80/a3/0a/5e/Manly1_thumb_medium.jpg", "count_of_followers": 18222, "count_of_following": 78, "count_of_designs": 584, "accepts_tips": true, "is_following": false, "location": "", "cover": "https://cdn.thingiverse.com/renders/8a/1e/7f/05/ab/dice2_preview_large.jpg"}, "is_private": null, "is_purchased": null, "is_published": null, "comment_count": 2, "like_count": 245, "tags": [{"name": "chicken", "tag": "chicken", "url": "https://api.thingiverse.com/tags/chicken", "count": 501, "things_url": "https://api.thingiverse.com/tags/chicken/things", "absolute_url": "https://www.thingiverse.com/tag:chicken"}, {"name": "chickens", "tag": "chickens", "url": "https://api.thingiverse.com/tags/chickens", "count": 67, "things_url": "https://api.thingiverse.com/tags/chickens/things", "absolute_url": "https://www.thingiverse.com/tag:chickens"}, {"name": "dnd", "tag": "dnd", "url": "https://api.thingiverse.com/tags/dnd", "count": 11070, "things_url": "https://api.thingiverse.com/tags/dnd/things", "absolute_url": "https://www.thingiverse.com/tag:dnd"}, {"name": "mount", "tag": "mount", "url": "https://api.thingiverse.com/tags/mount", "count": 18649, "things_url": "https://api.thingiverse.com/tags/mount/things", "absolute_url": "https://www.thingiverse.com/tag:mount"}, {"name": "mounts", "tag": "mounts", "url": "https://api.thingiverse.com/tags/mounts", "count": 116, "things_url": "https://api.thingiverse.com/tags/mounts/things", "absolute_url": "https://www.thingiverse.com/tag:mounts"}], "is_nsfw": false}]